pyplas/__init__.py
pyplas/plasma/__init__.py
pyplas/plasma/plasma.py
pyplas/species/__init__.py
pyplas/species/species.py
pyplas-0.2.1.dist-info/LICENSE
pyplas-0.2.1.dist-info/METADATA
pyplas-0.2.1.dist-info/WHEEL
pyplas-0.2.1.dist-info/top_level.txt
pyplas-0.2.1.dist-info/RECORD
