Metadata-Version: 2.1
Name: pyplas
Version: 0.2.1
Summary: Basic library for low-temperature plasmas.
Home-page: https://github.com/mimurrayy/pyplas
Author: Julian Held
Author-email: julian.held@umn.edu
License: MIT
Platform: any
Classifier: Programming Language :: Python :: 3
Classifier: License :: OSI Approved :: MIT License
Classifier: Operating System :: OS Independent
Requires-Python: >=3.8.1
License-File: LICENSE
Requires-Dist: numpy (>=1.19.5)
Requires-Dist: scipy (>=1.6.0)
Requires-Dist: mendeleev (>=0.13.0)
